src/__init__.py
src/cli.py
src/core.py
src/templates/stellar-core.cfg.public
src/templates/stellar-core.cfg.testnet
stellar_core_catchup-0.1.0.dist-info/LICENSE
stellar_core_catchup-0.1.0.dist-info/METADATA
stellar_core_catchup-0.1.0.dist-info/WHEEL
stellar_core_catchup-0.1.0.dist-info/entry_points.txt
stellar_core_catchup-0.1.0.dist-info/RECORD
