Metadata-Version: 2.1
Name: stellar-core-catchup
Version: 0.1.0
Summary: Efficiently synchronize a Stellar Core validator node
Author: overcat
Author-email: 4catcode@gmail.com
Requires-Python: >=3.8,<4.0
Classifier: Programming Language :: Python :: 3
Classifier: Programming Language :: Python :: 3.8
Classifier: Programming Language :: Python :: 3.9
Classifier: Programming Language :: Python :: 3.10
Classifier: Programming Language :: Python :: 3.11
Classifier: Programming Language :: Python :: 3.12
Requires-Dist: click (>=8.1.7,<9.0.0)
Requires-Dist: dataclasses-json (>=0.6.7,<0.7.0)
Requires-Dist: jinja2 (>=3.1.4,<4.0.0)
